Actifio/ActSupportClasses.py
Actifio/Actifio.py
Actifio/__init__.py
Actifio/actexceptions.py
Actifio/formatting.py
Actifio-1.0.5.data/scripts/actgentoken
Actifio-1.0.5.dist-info/LICENSE
Actifio-1.0.5.dist-info/METADATA
Actifio-1.0.5.dist-info/WHEEL
Actifio-1.0.5.dist-info/top_level.txt
Actifio-1.0.5.dist-info/RECORD
