Metadata-Version: 2.1
Name: Actifio
Version: 1.0.5
Summary: Actifio Restful API wrapper for Python.
Home-page: https://github.com/Actifio/actifio-python-package
Author: Kosala Atapattu
Author-email: kosala.atapattu@actifio.com
License: UNKNOWN
Platform: UNKNOWN
Classifier: Programming Language :: Python :: 2.7
Classifier: Programming Language :: Python :: 3
Classifier: License :: OSI Approved :: MIT License
Classifier: Operating System :: OS Independent
Requires-Dist: urllib3
